.pep8
MANIFEST.in
README.rst
TODO.rst
distribute_setup.py
gcaff.1
gcaff.desktop
gpl-3.0.txt
screenshot.png
setup.py
gcaff/__init__.py
gcaff/__main__.py
gcaff/gpg.py
gcaff/mail.py
gcaff/ui.py
gcaff/version.py
gcaff.egg-info/PKG-INFO
gcaff.egg-info/SOURCES.txt
gcaff.egg-info/dependency_links.txt
gcaff.egg-info/entry_points.txt
gcaff.egg-info/top_level.txt