Metadata-Version: 1.1
Name: gcaff
Version: 0.4
Summary: graphical OpenPGP signing assistant
Home-page: https://github.com/frasertweedale/gcaff
Author: Fraser Tweedale
Author-email: frase@frase.id.au
License: UNKNOWN
Platform: UNKNOWN
Classifier: Development Status :: 3 - Alpha
Classifier: Environment :: X11 Applications :: GTK
Classifier: Intended Audience :: End Users/Desktop
Classifier: Intended Audience :: Information Technology
Classifier: License :: OSI Approved :: GNU General Public License v3 or later (GPLv3+)
Classifier: Programming Language :: Python :: 2.7
Classifier: Topic :: Communications :: Email
Classifier: Topic :: Security :: Cryptography
